{
    "dset_name": "charades",
    "eval_split_name": "val",
    "debug": false,
    "results_root": "results",
    "exp_id": "fawl",
    "seed": 2018,
    "device": 0,
    "device_ids": [
        1
    ],
    "num_workers": 8,
    "no_core_driver": false,
    "no_pin_memory": false,
    "lr": 0.00015,
    "lr_warmup_proportion": 0.01,
    "wd": 0.01,
    "n_epoch": 100,
    "max_es_cnt": 10,
    "bsz": 128,
    "eval_query_bsz": 500,
    "eval_context_bsz": 500,
    "eval_untrained": false,
    "grad_clip": -1,
    "margin": 0.2,
    "train_span_start_epoch": 0,
    "hard_negative_start_epoch": 20,
    "hard_pool_size": 20,
    "max_sub_l": 50,
    "max_desc_l": 30,
    "max_ctx_l": 64,
    "train_path": null,
    "eval_path": null,
    "sub_feat_size": 768,
    "q_feat_size": 1024,
    "no_norm_vfeat": false,
    "no_norm_tfeat": false,
    "vid_feat_size": null,
    "max_position_embeddings": 300,
    "hidden_size": 384,
    "n_heads": 4,
    "input_drop": 0.1,
    "drop": 0.1,
    "initializer_range": 0.02,
    "model_name": "FAWL",
    "root_path": "data/",
    "visual_feature": "i3d_rgb_lgi",
    "collection": "charades",
    "map_size": 32,
    "use_sub": false,
    "clip_scale_w": 0.4,
    "frame_scale_w": 0.6,
    "visual_feat_dim": 1024,
    "num_gauss_center": 16,
    "num_gauss_width": 10,
    "width_lower_bound": 0.05,
    "width_upper_bound": 1,
    "window_size_inc": 1,
    "sigma": 9,
    "gamma": 0,
    "num_props": 8,
    "clip_proposal": "center_based",
    "proposal_method": "handcraft_width",
    "eval_ngc": 32,
    "eval_ngw": 10,
    "props_topk": 1,
    "pooling_ksize": 4,
    "pooling_stride": 4,
    "conv_ksize": 4,
    "conv_stride": 1,
    "global_sample": false,
    "alpha1": 1,
    "alpha2": 1,
    "alpha3": 1,
    "alpha4": 1.0,
    "alpha5": 1.0,
    "beta1": 1,
    "beta2": 1,
    "intra_margin": 0.2,
    "frame_feat_sample": "fixed",
    "train_data_ratio": 1.0,
    "eval_data_ratio": 1.0,
    "shared_trans": "true",
    "vocab_size": null,
    "word_dim": 300,
    "npev": 10,
    "max_vcmr_props": 1000,
    "warmup_epoch": 7,
    "results_dir": "data/charades/results/VCMR/2024_09_02_14_40_13-charades-fawl",
    "ckpt_filepath": "data/charades/results/VCMR/2024_09_02_14_40_13-charades-fawl/model.ckpt",
    "train_log_filepath": "data/charades/results/VCMR/2024_09_02_14_40_13-charades-fawl/train.log.txt",
    "eval_log_filepath": "data/charades/results/VCMR/2024_09_02_14_40_13-charades-fawl/eval.log.txt",
    "tensorboard_log_dir": "data/charades/results/VCMR/2024_09_02_14_40_13-charades-fawl/tensorboard_log"
}